usaddress/__init__.py
usaddress/usaddr.crfsuite
usaddress-0.5.15.dist-info/licenses/LICENSE
usaddress-0.5.15.dist-info/METADATA
usaddress-0.5.15.dist-info/WHEEL
usaddress-0.5.15.dist-info/top_level.txt
usaddress-0.5.15.dist-info/RECORD
